aiohubot_flowdock.py
aiohubot_flowdock-0.1.2.dist-info/LICENSE
aiohubot_flowdock-0.1.2.dist-info/METADATA
aiohubot_flowdock-0.1.2.dist-info/WHEEL
aiohubot_flowdock-0.1.2.dist-info/top_level.txt
aiohubot_flowdock-0.1.2.dist-info/RECORD
