Metadata-Version: 2.1
Name: aiohubot-flowdock
Version: 0.1.2
Summary: UNKNOWN
Home-page: https://github.com/LFLab/aiohubot-flowdock
Author: Lanfon
Author-email: lanfon72@gmail.com
License: UNKNOWN
Platform: UNKNOWN
Classifier: Development Status :: 3 - Alpha
Classifier: Intended Audience :: Developers
Classifier: License :: OSI Approved :: MIT License
Classifier: Operating System :: OS Independent
Classifier: Programming Language :: Python :: 3.6
Classifier: Programming Language :: Python :: 3.7
Requires-Python: >=3.6
Requires-Dist: aiohubot
Requires-Dist: aioflowdock
